super_scad_smooth_profile/Rough.py
super_scad_smooth_profile/SmoothProfile2D.py
super_scad_smooth_profile/SmoothProfile3D.py
super_scad_smooth_profile/SmoothProfileParams.py
super_scad_smooth_profile/__init__.py
super_scad_smooth_profile-0.6.3.dist-info/LICENSE
super_scad_smooth_profile-0.6.3.dist-info/METADATA
super_scad_smooth_profile-0.6.3.dist-info/WHEEL
super_scad_smooth_profile-0.6.3.dist-info/RECORD
