Metadata-Version: 2.3
Name: Super-SCAD-Smooth-Profile
Version: 0.6.3
Summary: Interface for Smooth profiles.
License: MIT
Keywords: OpenSCAD,SuperSCAD,Smooth Profile
Author: P.R. Water
Author-email: p.r.water@setbased.nl
Requires-Python: >=3.13.0,<4.0.0
Classifier: Development Status :: 5 - Production/Stable
Classifier: Intended Audience :: Developers
Classifier: Intended Audience :: Manufacturing
Classifier: License :: OSI Approved :: MIT License
Classifier: Programming Language :: Python :: 3
Classifier: Programming Language :: Python :: 3.13
Classifier: Topic :: Multimedia :: Graphics :: 3D Modeling
Classifier: Topic :: Software Development :: Code Generators
Requires-Dist: super-scad (>=0.11.0,<0.12.0)
Project-URL: Documentation, https://superscad.readthedocs.io/
Project-URL: Repository, https://github.com/SuperSCAD/SmoothProfile
